python_sdk/__init__.py
python_sdk/client/admin/admin_request_builder.py
python_sdk/client/admin/artifact_types/artifact_types_request_builder.py
python_sdk/client/admin/config/config_request_builder.py
python_sdk/client/admin/config/properties/item/with_property_name_item_request_builder.py
python_sdk/client/admin/config/properties/properties_request_builder.py
python_sdk/client/admin/export/export_request_builder.py
python_sdk/client/admin/import_/import_request_builder.py
python_sdk/client/admin/loggers/item/with_logger_item_request_builder.py
python_sdk/client/admin/loggers/loggers_request_builder.py
python_sdk/client/admin/role_mappings/item/with_principal_item_request_builder.py
python_sdk/client/admin/role_mappings/role_mappings_request_builder.py
python_sdk/client/admin/rules/item/with_rule_item_request_builder.py
python_sdk/client/admin/rules/rules_request_builder.py
python_sdk/client/groups/groups_request_builder.py
python_sdk/client/groups/item/artifacts/artifacts_request_builder.py
python_sdk/client/groups/item/artifacts/item/meta/meta_request_builder.py
python_sdk/client/groups/item/artifacts/item/owner/owner_request_builder.py
python_sdk/client/groups/item/artifacts/item/rules/item/with_rule_item_request_builder.py
python_sdk/client/groups/item/artifacts/item/rules/rules_request_builder.py
python_sdk/client/groups/item/artifacts/item/state/state_request_builder.py
python_sdk/client/groups/item/artifacts/item/test/test_request_builder.py
python_sdk/client/groups/item/artifacts/item/versions/item/meta/meta_request_builder.py
python_sdk/client/groups/item/artifacts/item/versions/item/references/references_request_builder.py
python_sdk/client/groups/item/artifacts/item/versions/item/state/state_request_builder.py
python_sdk/client/groups/item/artifacts/item/versions/item/with_version_item_request_builder.py
python_sdk/client/groups/item/artifacts/item/versions/versions_request_builder.py
apicurioregistrydkpreview-2.4.3.dist-info/METADATA
apicurioregistrydkpreview-2.4.3.dist-info/WHEEL
apicurioregistrydkpreview-2.4.3.dist-info/RECORD
