Metadata-Version: 2.1
Name: apicurioregistrydkpreview
Version: 2.4.3
Summary: 
Home-page: https://github.com/apicurio/apicurio-registry
License: Apache 2.0
Keywords: apicurio,registry
Author: Andrea Peruffo
Author-email: andrea.peruffo1982@gmail.com
Requires-Python: >=3.11,<4.0
Classifier: License :: Other/Proprietary License
Classifier: Programming Language :: Python :: 3
Classifier: Programming Language :: Python :: 3.11
Requires-Dist: microsoft-kiota-abstractions (>=0.5.1,<0.6.0)
Requires-Dist: microsoft-kiota-http (>=0.4.1,<0.5.0)
Requires-Dist: microsoft-kiota-serialization-json (>=0.3.2,<0.4.0)
Requires-Dist: microsoft-kiota-serialization-text (>=0.2.0,<0.3.0)
Project-URL: Repository, https://github.com/apicurio/apicurio-registry
